<?xml version="1.0" encoding="UTF-8"?>
<settings>
  <localRepository>/Users/jdcasey/.m2/repository</localRepository>
  <mirrors>
    <mirror>
      <id>nexus</id>
      <name>Local Nexus</name>
      <mirrorOf>external:*</mirrorOf>
      <url>http://localhost:8081/nexus/service/local/capture/resolve/public</url>
      <!-- <url>http://localhost:8081/nexus/service/local/capture/resolve/public/jboss</url> -->
      <!-- <url>http://localhost:8081/nexus/service/local/capture/resolve/public/jb-release</url> -->
    </mirror>
  </mirrors>
  <pluginGroups>
    <pluginGroup>com.redhat.rcm.nexus</pluginGroup>
  </pluginGroups>
  <servers>
    <server>
      <id>nexus</id>
      <username>jdcasey</username>
      <password>l3tm31n</password>
    </server>
    <server>
      <id>central</id>
      <username>jdcasey</username>
      <password>l3tm31n</password>
    </server>
    <!-- <server>
      <id>nexus</id>
      <username>admin</username>
      <password>admin123</password>
    </server>
    <server>
      <id>central</id>
      <username>admin</username>
      <password>admin123</password>
    </server> -->
  </servers>
</settings>
